pymjdcal/__init__.py
pymjdcal/__main__.py
pymjdcal/pymjdcal.py
pymjdcal-0.0.1.dist-info/LICENSE
pymjdcal-0.0.1.dist-info/METADATA
pymjdcal-0.0.1.dist-info/WHEEL
pymjdcal-0.0.1.dist-info/top_level.txt
pymjdcal-0.0.1.dist-info/RECORD
