Metadata-Version: 2.1
Name: pymjdcal
Version: 0.0.1
Summary: MJD Calender in Python
Home-page: https://github.com/tungthai92/pymjdcal
Author: Tung Thai
Author-email: tung.t.thai92@gmail.com
License: UNKNOWN
Project-URL: Bug Tracker, https://github.com/tungthai92/pymjdcal/issues
Platform: UNKNOWN
Classifier: Programming Language :: Python :: 3
Classifier: License :: OSI Approved :: MIT License
Classifier: Operating System :: OS Independent
Requires-Python: >=3.7
License-File: LICENSE
Requires-Dist: julian (==0.14)
